redoc/__init__.py
redoc/cli.py
redoc/core.py
redoc/exceptions.py
redoc-0.2.2.dist-info/licenses/LICENSE
redoc-0.2.2.dist-info/METADATA
redoc-0.2.2.dist-info/WHEEL
redoc-0.2.2.dist-info/entry_points.txt
redoc-0.2.2.dist-info/top_level.txt
redoc-0.2.2.dist-info/RECORD
