Metadata-Version: 2.4
Name: redoc
Version: 0.2.2
Summary: Universal document converter with template support, OCR, and AI-powered processing. Convert between PDF, DOCX, HTML, XML, JSON, EPUB and more with a simple CLI or Python API.
Author-email: Tom Sapletta <info@softreck.dev>
Maintainer-email: Tom Sapletta <info@softreck.dev>
License: Apache-2.0
Project-URL: homepage, https://github.com/text2doc/redoc
Project-URL: repository, https://github.com/text2doc/redoc
Project-URL: documentation, https://text2doc.github.io/redoc
Project-URL: changelog, https://github.com/text2doc/redoc/blob/main/CHANGELOG.md
Project-URL: bug-tracker, https://github.com/text2doc/redoc/issues
Project-URL: source, https://github.com/text2doc/redoc
Project-URL: download, https://pypi.org/project/redoc/#files
Project-URL: discussions, https://github.com/text2doc/redoc/discussions
Requires-Python: <4.0,>=3.9
License-File: LICENSE
Requires-Dist: requests>=2.31.0
Requires-Dist: pydantic>=2.5.0
Requires-Dist: click>=8.1.7
Requires-Dist: rich[all]>=13.0.0
Requires-Dist: pyyaml>=6.0.1
Requires-Dist: tabulate<1.0.0,>=0.9.0
Requires-Dist: jinja2>=3.1.2
Requires-Dist: pathlib>=1.0.1
Requires-Dist: dataclasses-json>=0.6.3
Requires-Dist: typing-extensions>=4.8.0
Requires-Dist: python-dotenv>=1.0.0
Requires-Dist: pypdf2<4.0.0,>=3.0.1
Requires-Dist: reportlab<5.0.0,>=4.4.1
Provides-Extra: python-docx
Requires-Dist: python-docx>=1.1.0; extra == "python-docx"
Provides-Extra: pypdf
Requires-Dist: pypdf>=3.17.0; extra == "pypdf"
Provides-Extra: lxml
Requires-Dist: lxml>=5.1.0; extra == "lxml"
Provides-Extra: python-multipart
Requires-Dist: python-multipart>=0.0.6; extra == "python-multipart"
Provides-Extra: fastapi
Requires-Dist: fastapi>=0.104.0; extra == "fastapi"
Provides-Extra: uvicorn
Requires-Dist: uvicorn>=0.24.0; extra == "uvicorn"
Provides-Extra: mkdocs
Requires-Dist: mkdocs-material[imaging]>=9.6.14; extra == "mkdocs"
Provides-Extra: mkdocs-extensions
Requires-Dist: mkdocs-material-extensions>=1.3.1; extra == "mkdocs-extensions"
Provides-Extra: pdf2image
Requires-Dist: pdf2image>=1.17.0; extra == "pdf2image"
Provides-Extra: pillow
Requires-Dist: pillow>=10.2.0; extra == "pillow"
Provides-Extra: openai
Requires-Dist: openai>=1.3.0; extra == "openai"
Provides-Extra: cli
Requires-Dist: rich-click>=1.7.0; extra == "cli"
Provides-Extra: server
Requires-Dist: fastapi; extra == "server"
Requires-Dist: uvicorn; extra == "server"
Requires-Dist: python-multipart; extra == "server"
Provides-Extra: ai
Requires-Dist: openai; extra == "ai"
Requires-Dist: numpy>=1.24.0; extra == "ai"
Requires-Dist: scikit-learn>=1.3.0; extra == "ai"
Provides-Extra: cloud
Requires-Dist: boto3>=1.28.0; extra == "cloud"
Requires-Dist: azure-storage-blob>=12.17.0; extra == "cloud"
Requires-Dist: google-cloud-storage>=2.10.0; extra == "cloud"
Provides-Extra: export
Requires-Dist: markdown>=3.4.0; extra == "export"
Requires-Dist: pandoc>=2.3.0; extra == "export"
Provides-Extra: dev
Requires-Dist: pytest>=7.4.3; extra == "dev"
Requires-Dist: pytest-cov>=4.1.0; extra == "dev"
Requires-Dist: pytest-mock>=3.12.0; extra == "dev"
Requires-Dist: black>=23.11.0; extra == "dev"
Requires-Dist: flake8>=6.1.0; extra == "dev"
Requires-Dist: mypy>=1.7.1; extra == "dev"
Requires-Dist: isort>=5.12.0; extra == "dev"
Requires-Dist: pre-commit>=3.6.0; extra == "dev"
Requires-Dist: sphinx>=7.2.6; extra == "dev"
Requires-Dist: sphinx-rtd-theme>=1.3.0; extra == "dev"
Requires-Dist: mkdocs>=1.5.3; extra == "dev"
Requires-Dist: mkdocs-material>=9.4.8; extra == "dev"
Requires-Dist: jupyterlab>=4.0.9; extra == "dev"
Requires-Dist: ipython>=8.17.2; extra == "dev"
Requires-Dist: pytest-asyncio>=0.21.1; extra == "dev"
Requires-Dist: pytest-xdist>=3.5.0; extra == "dev"
Requires-Dist: pytest-benchmark>=4.0.0; extra == "dev"
Requires-Dist: responses>=0.24.1; extra == "dev"
Requires-Dist: factory-boy>=3.3.0; extra == "dev"
Requires-Dist: faker>=20.1.0; extra == "dev"
Requires-Dist: freezegun>=1.2.2; extra == "dev"
Requires-Dist: mkdocstrings[python]>=0.29.1; extra == "dev"
Requires-Dist: mkdocs-minify-plugin>=0.8.0; extra == "dev"
Dynamic: license-file
